{
  "cell_line_id": "AIBNi001",
  "saved_on": "2025-11-05T22:49:08.639273",
  "status": "working",
  "curated_data": {
    "basic_data": [
      {
        "hpscreg_name": "AIBNi001",
        "cell_type": "hiPSC",
        "frozen": "True"
      }
    ],
    "contact": [
      {
        "first_name": "Test",
        "last_name": "User",
        "e_mail": "test@example.com"
      }
    ],
    "publications": [
      {
        "title": "Test Publication",
        "journal": "Test Journal",
        "year": "2024"
      }
    ]
  }
}